{
  "timestamp": "2025-12-29T14:12:05",
  "url": "https://www.sueddeutsche.de/",
  "response": {
    "status": 200
  },
  "scripts": [
    {
      "type": "text/javascript",
      "src": "https://wni4spsbqo.kameleoon.eu/kameleoon.js",
      "id": "kameleoonScript",
      "text": null
    },
    {
      "type": "module",
      "src": "https://www.sueddeutsche.de/szde-assets/szhp-pages/szde-pages/js/department-page-C47xb23R.mjs",
      "id": null,
      "text": null
    },
    {
      "type": "module",
      "src": "https://www.sueddeutsche.de/szde-assets/js/header-vendors-d3cb65f12bf616fe43a3.mjs",
      "id": null,
      "text": null
    },
    {
      "type": "module",
      "src": "https://www.sueddeutsche.de/szde-assets/js/header-full-06130b6b84c09eb7fba5.mjs",
      "id": null,
      "text": null
    }
  ],
  "articles": [
    {
      "title": "2026 wird ein GROSSES Jahr für die USA",
      "teaser": "US-Präsident Trump versucht, die Geschichte des Landes als Heldengeschichte umzuschreiben.",
      "url": "https://www.sueddeutsche.de/politik/usa-trump-geschichte-revisionismus-sklaverei-li.3349206",
      "image_url": "https://www.sueddeutsche.de/2025/12/28/9076a268-3b5b-4302-bd19-ac1f41863e97.jpg?rect=0,455,3000,1687&width=1000&fm=jpeg&q=60"
    },
    {
      "title": "„Die Maga-Bewegung wird ohne Trump zerfallen“",
      "teaser": "Rich Logis war fanatischer Anhänger des US-Präsidenten. Jetzt hilft er anderen Menschen, aus der Maga-Bewegung auszusteigen – und hat Sorge, was auf diese folgen könnte.",
      "url": "https://www.sueddeutsche.de/politik/rich-logis-ausstieg-trump-maga-bewegung-li.3349888"
    },
    {
      "title": "„Ich glaube nicht, dass wir lange so weitermachen können“",
      "teaser": "Anthony Fauci, fast 40 Jahre lang oberster Seuchenschützer der USA und Berater von sieben Präsidenten, spricht über seine Enttäuschung über die aktuelle US-Gesundheitspolitik.",
      "url": "https://www.sueddeutsche.de/gesundheit/anthony-fauci-gesundheit-usa-corona-impfung-li.3349768"
    },
    {
      "title": "Nachruf:Brigitte Bardot hat gemacht, was sie wollte",
      "url": "https://www.sueddeutsche.de/projekte/artikel/kultur/brigitte-bardot-film-nachruf-bardot-schauspielerin-e794082/",
      "image_url": "https://www.sueddeutsche.de/2025/12/29/87bf3f43-158f-4e47-b0e6-83a87e82b36f.jpg?rect=1055,98,1107,1476&width=178&fm=jpeg&q=60"
    },
    {
      "title": "Psychologie:Was ist eine gute Kindheit?",
      "url": "https://www.sueddeutsche.de/wissen/kindheit-bedingungen-kinder-deutschland-li.3322899",
      "image_url": "https://www.sueddeutsche.de/2025/12/16/3b31e52a-49c9-44dc-ac7d-01aab220e6a0.jpg?rect=659,189,762,1016&width=178&fm=jpeg&q=60"
    },
    {
      "title": "London:Annette Dittert verlässt den NDR. Ein Protest",
      "url": "https://www.sueddeutsche.de/medien/annette-dittert-england-london-ard-tagesschau-li.3358365",
      "image_url": "https://www.sueddeutsche.de/2025/12/23/30894b06-3ce7-4ba0-b3bd-667da8079b7e.jpg?width=178&ar=3:4&fit=crop&fm=jpeg&q=60"
    },
    {
      "title": "Fotoboxen:Das Geheimnis einer Blitzkarriere",
      "url": "https://sz-magazin.sueddeutsche.de/leben-und-gesellschaft/fotoautomat-jubilaeum-essay-foto-authentisch-95589",
      "image_url": "https://www.sueddeutsche.de/2025/11/10/960bbd6a-b420-4d34-8554-2429ed2ab5b1.jpg?rect=221,586,405,541&width=178&fm=jpeg&q=60"
    },
    {
      "title": "SZ PlusKrieg in der Ukraine:Treffen von Selenskij und Trump endet ohne Durchbruch",
      "url": "https://www.sueddeutsche.de/politik/trump-selenskij-friedensprozess-mar-a-lago-li.3360347",
      "image_url": "https://www.sueddeutsche.de/2025/12/29/c8b85748-a01e-46cb-b8ca-48a7ee545d2f.jpg?rect=742,643,2429,1822&width=115&fm=jpeg&q=60"
    },
    {
      "title": "Gesundheitssystem:Kassenärzte-Chef fordert Gebühr bei jedem Arztbesuch",
      "url": "https://www.sueddeutsche.de/politik/krankenkassen-arzt-gebuehr-li.3360549",
      "image_url": "https://www.sueddeutsche.de/2025/12/29/658c836d-f209-4b50-ada1-191a35f349bf.jpg?rect=288,261,3058,2293&width=115&fm=jpeg&q=60"
    },
    {
      "title": "Unglück am Laubeneck:14-Jähriger stürzt tödlich am Berg",
      "url": "https://www.sueddeutsche.de/bayern/unterammergau-bayern-laubeneck-berg-sturz-14-jaehriger-tod-li.3360721",
      "image_url": "https://www.sueddeutsche.de/2025/04/08/5d5c3ae6-a5cf-44a1-8d39-5a7e2a9a4c4e.jpeg?rect=276,0,3448,2586&width=115&fm=jpeg&q=60"
    },
    {
      "title": "München:Surf-Verein will weitere Eskalation um die Eisbachwelle verhindern",
      "url": "https://www.sueddeutsche.de/muenchen/muenchen-eisbachwelle-wiederherstellung-eskalation-annaeherung-li.3360565",
      "image_url": "https://www.sueddeutsche.de/2025/12/29/bb883f88-7f61-4a3b-a462-00be11f979ca.jpg?rect=501,0,2997,2248&width=115&fm=jpeg&q=60"
    },
    {
      "title": "„Ernste Warnung“:China beginnt militärisches Großmanöver rund um Taiwan",
      "url": "https://www.sueddeutsche.de/politik/china-militaeruebung-taiwan-li.3360523",
      "image_url": "https://www.sueddeutsche.de/2025/12/29/2220a0ad-c83c-447e-ac93-31c589a9e5b1.jpg?rect=428,349,1405,1054&width=115&fm=jpeg&q=60"
    },
    {
      "title": "Meinung:Wenn Trump die Europäer lobt, wird es gefährlich",
      "teaser": "„Russland wünscht sich den Erfolg der Ukraine“, behauptet der US-Präsident in Mar-a-Lago. Sein ukrainischer Amtskollege nimmt die Worte sichtlich verwundert und leicht amüsiert auf.",
      "url": "https://www.sueddeutsche.de/meinung/friedensverhandlungen-ukraine-usa-trump-kommentar-li.3360638",
      "image_url": "https://www.sueddeutsche.de/2025/12/29/4dcdead9-914a-4211-a57e-078b7a1015b7.jpg?rect=0,0,4000,2250&width=1000&fm=jpeg&q=60"
    },
    {
      "title": "Live:Bizarre Trump-Aussage irritiert Selenskij",
      "teaser": "„Russland wünscht sich den Erfolg der Ukraine“, behauptet der US-Präsident in Mar-a-Lago. Sein ukrainischer Amtskollege nimmt die Worte sichtlich verwundert und leicht amüsiert auf.",
      "url": "https://www.sueddeutsche.de/politik/ukraine-krieg-newsblog-trump-putin-selenskij-selbstkontrolle-mar-a-lago-li.3353907"
    },
    {
      "title": "Sie gießen Sirup über die bittere Realität",
      "teaser": "Donald Trump kündigt einen „großartigen Deal“ an, der zu „nahezu 95 Prozent“ fertig sein soll. Wer würde so ein Produkt kaufen? Wolodimir Selenskij sicher nicht.",
      "url": "https://www.sueddeutsche.de/kultur/trump-selenskyj-frieden-krieg-ukraine-konflikt-gastbeitrag-li.3360578"
    },
    {
      "title": "Was sich 2026 alles ändert:Nicht nur die Krankenversicherung wird teurer",
      "teaser": "Die Sozialabgaben steigen, die Kfz-Versicherung kostet mehr, Mindestlohn und Unterhalt werden erhöht. Wo nächstes Jahr mehr zu zahlen ist – und was besser wird.",
      "url": "https://www.sueddeutsche.de/wirtschaft/steuern-und-abgaben-versicherungen-was-sich-2026-aendert-li.3335053",
      "image_url": "https://www.sueddeutsche.de/2025/12/19/ffa1e584-ca45-4339-9a68-abac7a3c3ec6.jpg?rect=0,173,3000,1687&width=630&fm=jpeg&q=60"
    },
    {
      "title": "MeinungDemokratie:Die Regierung Merz darf so nicht weiterdilettieren, 2026 braucht es einen Neuanfang",
      "url": "https://www.sueddeutsche.de/meinung/merz-koalition-bundesregierung-reformen-krise-kommentar-li.3354712"
    },
    {
      "title": "Nachruf:Ein Rockstar des Theaters",
      "teaser": "Bevor Peter Sattmann ein Garant des Serienfernsehens wurde, war er der Zuschauermagnet in Claus Peymanns Stuttgarter Ensemble. Jetzt ist der Schauspieler kurz vor seinem 78. Geburtstag gestorben.",
      "url": "https://www.sueddeutsche.de/kultur/nachruf-peter-sattmann-stuttgart-claus-peymann-gestorben-li.3360587",
      "image_url": "https://www.sueddeutsche.de/2025/12/29/9148ade0-06eb-4ef0-9fd5-d422fda9caf8.jpg?rect=0,206,4000,2250&width=630&fm=jpeg&q=60"
    },
    {
      "title": "Leerstand trotz Wohnungsnot:Münchens Geisterhäuser",
      "teaser": "Das Wohnproblem ist in München brisant wie in keiner anderen deutschen Stadt – trotzdem stehen hier ganze Häuser leer. Wie kann das sein? Zehn Beispiele und ihre Geschichte.",
      "url": "https://www.sueddeutsche.de/projekte/artikel/muenchen/muenchen-wohnhaeuser-mieten-leerstand-e231990/",
      "image_url": "https://www.sueddeutsche.de/2025/12/23/54850327-c3a6-4332-9175-4bd6c6bf5f7f.jpg?rect=0,0,2500,1406&width=630&fm=jpeg&q=60"
    },
    {
      "title": "SZ MagazinPhilosophie:Dieser Mann kennt den Sinn des Lebens",
      "teaser": "Der Philosoph Michael Zichy hat eine erstaunlich einfache Antwort auf die vielleicht größte Frage der Menschheit und weiß auch, wie diese uns gesünder machen und die Gesellschaft stärken kann.",
      "url": "https://sz-magazin.sueddeutsche.de/leben-und-gesellschaft/interview-michael-zichy-philosophie-95730",
      "image_url": "https://www.sueddeutsche.de/2025/12/11/606306e2-f228-4486-889d-b81464400ac3.jpg?rect=124,57,636,357&width=630&fm=jpeg&q=60"
    },
    {
      "title": "Entwaldungsverordnung:Wer schützt jetzt den Ort, wo Jaguar und Schwarzspecht hausen?",
      "url": "https://www.sueddeutsche.de/meinung/eu-green-deal-wald-klimaschutz-li.3334115",
      "image_url": "https://www.sueddeutsche.de/2025/12/09/cc3049f9-1380-479a-b546-5af70e95ffdd.jpg?rect=0,209,4000,2250&width=630&fm=jpeg&q=60"
    },
    {
      "title": "Eisbachwelle:München läuft Gefahr, sich im großen Stil zu blamieren",
      "url": "https://www.sueddeutsche.de/muenchen/eisbach-welle-surfen-muenchen-streit-kommentar-li.3360289",
      "image_url": "https://www.sueddeutsche.de/2024/07/15/ebd0de99-a6dc-4210-96ea-c32ad3f51a47.png?width=45&ar=1:1&fit=crop&fm=png&q=60",
      "image_title": "Portrait Ressortleiter René Hofmann"
    },
    {
      "title": "Silvesterkracherei:Auch legal gekaufte Böller können einem die Augen zerfetzen",
      "url": "https://www.sueddeutsche.de/meinung/boeller-raketen-silvester-li.3360301",
      "image_url": "https://www.sueddeutsche.de/2024/07/15/c41e4f7e-6f8c-4720-ac25-7eef9c1c0813.png?width=45&ar=1:1&fit=crop&fm=png&q=60",
      "image_title": "Portrait Stellvertretender Ressortleiter Felix Hütten"
    },
    {
      "title": "Demokratie:Vorsicht, wenn Trump, die AfD und Springer von „Meinungsfreiheit“ reden",
      "url": "https://www.sueddeutsche.de/meinung/trump-afd-meinungsfreiheit-zensur-usa-deutschland-kommentar-li.3360318",
      "image_url": "https://www.sueddeutsche.de/2024/11/13/2ac34df7-975a-4208-beaa-d74311dd5298.png?width=45&ar=1:1&fit=crop&fm=png&q=60",
      "image_title": "Portrait Ressortleiter Meinung Detlef Esslinger"
    },
    {
      "title": "„Ich kann dir gar nicht zurückgeben, was du alles für mich getan hast“",
      "teaser": "Der Retter am Unfallort, die Ordensschwester, der verstorbene Vater: Wir haben unsere Leserinnen und Leser gefragt, wer in diesem Jahr ihr ganz persönlicher Alltagsheld war. Elf bewegende Antworten.",
      "url": "https://www.sueddeutsche.de/projekte/artikel/gesellschaft/danke-helden-2025-leser-e262053/",
      "image_url": "https://www.sueddeutsche.de/2025/12/18/5932d28a-830f-4c4a-ac08-ec79e27473f6.jpg?rect=0,0,1920,1080&width=1000&fm=jpeg&q=60"
    },
    {
      "title": "Safilo:„Das Brillengeschäft ist ziemlich kompliziert“",
      "teaser": "Wie entstehen Brillentrends? Und warum stehen Markennamen heute nicht mehr so sichtbar auf den Rahmen wie früher? Angelo Trocchia, Chef des italienischen Herstellers Safilo, spricht über die sehr spezielle Welt der Sehhilfen.",
      "url": "https://www.sueddeutsche.de/wirtschaft/brillenindustrie-blick-safilo-design-li.3335677",
      "image_url": "https://www.sueddeutsche.de/2025/12/12/94cc3064-12b9-424d-8375-f7970abd0e62.jpg?rect=0,1169,2668,1501&width=465&fm=jpeg&q=60"
    },
    {
      "title": "Tokio:Die Stadt der verlassenen Häuser",
      "teaser": "In Tokio stehen 900 000 Häuser und Wohnungen leer. Luxusappartements ebenso wie halb verrottende Geistergebäude. Die Gründe sind vielfältig, manchmal steckt ein längst vergangener Mord dahinter.",
      "url": "https://www.sueddeutsche.de/panorama/tokio-problem-haeuser-akiya-li.3351627",
      "image_url": "https://www.sueddeutsche.de/2025/12/28/dc8497b9-73ad-4e3b-89f1-5b79b7742909.jpg?rect=0,375,4000,2250&width=465&fm=jpeg&q=60"
    },
    {
      "title": "Was die Entwicklung der Asylzahlen aussagt",
      "teaser": "Im Wahlkampf hat die Bundesregierung einen Knallhartkurs in der Migration angekündigt. 2025 beantragten tatsächlich weniger Geflüchtete Asyl. Aber der Antritt der neuen Koalition hatte in der Statistik kaum einen erkennbaren Effekt.",
      "url": "https://www.sueddeutsche.de/politik/migrationswende-deutschland-asylzahlen-li.3351277"
    },
    {
      "title": "Autoindustrie:Spaniens stille E-Auto-Revolution",
      "teaser": "Milliardeninvestitionen, günstiger Strom und klare politische Signale: Während Deutschland noch über den Verbrenner streitet, baut Spanien seine Rolle als neue E-Auto-Hochburg Europas aus.",
      "url": "https://www.sueddeutsche.de/wirtschaft/spanien-elektroautos-martorell-vw-elektromobilitaet-cupra-li.3349803"
    },
    {
      "title": "München:Surf-Verein will weitere Eskalation um die Eisbachwelle verhindern",
      "teaser": "Die Surfer in München wollen ihren Antrag auf Wiederherstellung der Welle nun doch weiterverfolgen – wenn die Stadt einige ihrer als unerfüllbar empfundenen Auflagen anpasst. Über den aktuellen Stand im Wellenstreit.",
      "url": "https://www.sueddeutsche.de/muenchen/muenchen-eisbachwelle-wiederherstellung-eskalation-annaeherung-li.3360565",
      "image_url": "https://www.sueddeutsche.de/2025/12/29/bb883f88-7f61-4a3b-a462-00be11f979ca.jpg?rect=2,0,3996,2248&width=630&fm=jpeg&q=60"
    },
    {
      "title": "Kuriose Einsätze in München:Wenn die Polizei zuletzt lacht ...",
      "url": "https://www.sueddeutsche.de/muenchen/muenchen-kurioses-2025-polizei-feuerwehr-zoll-li.3352416",
      "image_url": "https://www.sueddeutsche.de/2025/12/23/31f258de-0af9-4c84-912c-d535a6591871.jpg?rect=0,105,678,509&width=217&fm=jpeg&q=60"
    },
    {
      "title": "München-Freimann:Auto beim Circus Krone in Flammen – Polizei vermutet Brandstiftung",
      "url": "https://www.sueddeutsche.de/muenchen/muenchen-circus-krone-zirkus-moegliche-brandstiftung-freimann-li.3360728",
      "image_url": "https://www.sueddeutsche.de/2025/12/29/6ec0ed1f-d4c7-40f8-9773-3bed556ec884.jpg?rect=333,0,3335,2501&width=217&fm=jpeg&q=60"
    },
    {
      "title": "Niclas Füllkrug bei der AC Milan:Eine große Bühne, um es doch noch mal allen zu zeigen",
      "teaser": "Niclas Füllkrug, vor nicht allzu langer Zeit noch Deutschlands bester Stürmer, wechselt nach verlorenen Jahren in der Premier League zur AC Milan. Immerhin: Ü30-Spieler sind dort sehr willkommen.",
      "url": "https://www.sueddeutsche.de/sport/fuellkrug-wechsel-transfer-mailand-ac-milan-serie-a-li.3360062",
      "image_url": "https://www.sueddeutsche.de/2025/12/28/438ba6d1-59a9-48e5-8adc-ee4e2350e31d.jpg?rect=0,58,4000,2250&width=630&fm=jpeg&q=60"
    },
    {
      "title": "Bayern Basketballer:Pesic beginnt mit der Reparatur",
      "url": "https://www.sueddeutsche.de/sport/basketball-bayern-pesic-trier-li.3360588",
      "image_url": "https://www.sueddeutsche.de/2025/12/29/58f4455d-afc5-4f4b-b457-c2d99e7bc301.jpg?rect=223,0,3555,2666&width=217&fm=jpeg&q=60"
    },
    {
      "title": "Reitsport:Warum immer mehr deutsche Veranstalter kapitulieren",
      "url": "https://www.sueddeutsche.de/sport/mannheim-fuenfsterne-csio-reitsport-deutschland-li.3358594",
      "image_url": "https://www.sueddeutsche.de/2025/12/22/b9218c9e-b6e6-41a1-8884-1ccd28a324ef.jpg?rect=523,119,3233,2425&width=217&fm=jpeg&q=60"
    },
    {
      "title": "Leute:Kim Kardashian erntet Kritik von Peta",
      "teaser": "Denn sie schenkte ihren vier Kindern zu Weihnachten jeweils einen Hundewelpen. Kate Winslet hat ihre ersten intimen Erfahrungen mit Mädchen gemacht. Und Collien Fernandes genießt Onlinedating.",
      "url": "https://www.sueddeutsche.de/panorama/kim-kardashian-peta-hundewelpen-kate-winslet-promis-li.3360601",
      "image_url": "https://www.sueddeutsche.de/2025/11/17/a5510437-6c70-42a0-9884-3b0715cb7372.jpg?rect=0,61,3392,1908&width=630&fm=jpeg&q=60"
    },
    {
      "title": "Chérie, jetzt wird es Rosen regnen",
      "teaser": "Brigitte Bardot und Gunter Sachs, das war nur ein kurzes Glück. Ihre Klatschspalten-Ehe aber trug zur deutsch-französischen Verständigung bei. Und schuf ihre eigenen Legenden.",
      "url": "https://www.sueddeutsche.de/kultur/brigitte-bardot-gunter-sachs-ehe-li.3360326",
      "image_url": "https://www.sueddeutsche.de/2025/12/28/5b7e7fb2-d733-4e6c-a761-f30c24e167a1.jpg?rect=314,158,3005,1690&width=465&fm=jpeg&q=60"
    },
    {
      "title": "SZ MagazinTrennung trotz Liebe:Wir waren ein Traumpaar – dann kam das Leben dazwischen",
      "teaser": "Ungleicher Kinderwunsch, Fernbeziehung über Länder hinweg, verschiedene Lebenspläne: Manche Paare entscheiden sich für eine Trennung, obwohl sie sich lieben. Wie unsere Autorin. Doch heute weiß sie, wie man über eine solche Trennung hinwegkommt.",
      "url": "https://sz-magazin.sueddeutsche.de/liebe-und-partnerschaft/trennung-wider-willen-trotz-liebe-95748",
      "image_url": "https://www.sueddeutsche.de/2025/12/22/4fc07d5e-ad1b-4b17-9b08-6020878af2c2.jpg?rect=0,179,2121,1193&width=465&fm=jpeg&q=60"
    },
    {
      "title": "Pop:„Ich meine, komm, wer hält so einem Vergleich schon stand?“",
      "teaser": "Das ewige soziale Experiment, das Bands sind: Neil Gust spielte mit Elliott Smith bei „Heatmiser“, als der plötzlich final brillant wurde und künstlerisch unerreichbar. Eine Geschichte über Geniekult, Eifersucht und Freundschaft.",
      "url": "https://www.sueddeutsche.de/kultur/elliott-smith-heatmiser-mic-city-sons-li.3341056",
      "image_url": "https://www.sueddeutsche.de/2025/12/24/72c86b29-50fa-4409-b4c1-b55014585f22.jpg?rect=0,401,2513,1414&width=465&fm=jpeg&q=60"
    },
    {
      "title": "Literatur:„Wie eine Insel der Glückseligkeit“",
      "teaser": "Holly Brickleys Debüt „Deep Cuts“ ist ein Coming-of-Age-Roman, der in den 2000ern spielt – noch vor Veröffentlichung hat die Kanadierin ihn an Hollywood verkauft. Woher kommt die riesige „Y2K“-Sehnsucht, die gerade überall zu spüren ist?",
      "url": "https://www.sueddeutsche.de/kultur/holly-brickley-deep-cuts-interview-li.3355144",
      "image_url": "https://www.sueddeutsche.de/2025/12/22/19c27e03-7c80-4eab-a6fd-b9c5f35e34a8.jpg?rect=0,217,4000,2250&width=465&fm=jpeg&q=60"
    },
    {
      "title": "Wordle: offizielle Version:Fünf Buchstaben, sechs Versuche – finden Sie das Wort?",
      "url": "https://www.sueddeutsche.de/raetsel/aktuell/wordle",
      "image_url": "https://www.sueddeutsche.de/2025/12/01/22c61208-59be-4a13-9042-f274578e99a4.png?rect=0,0,832,624&width=217&fm=png&q=60"
    },
    {
      "title": "Kreuzworträtsel: täglich neu:15 mal 15 – füllt Ihr Wissen alle Felder?",
      "url": "https://www.sueddeutsche.de/raetsel/aktuell/kreuzwortraetsel/",
      "image_url": "https://www.sueddeutsche.de/2024/03/18/c2ba0d6b-b70e-4674-9ac5-b474e484824a.png?rect=0,0,832,624&width=217&fm=png&q=60"
    },
    {
      "title": "Sudoku: von leicht bis schwer:1 bis 9 – bekommen Sie’s auf die Reihe?",
      "url": "https://www.sueddeutsche.de/raetsel/aktuell/sudoku",
      "image_url": "https://www.sueddeutsche.de/2025/12/01/c31ccf96-fe85-4b66-9834-413af080d9eb.png?rect=0,0,832,624&width=217&fm=png&q=60"
    },
    {
      "title": "Str8ts: jeden Tag anders:Bauen Sie Zahlenstraßen – kreuz und quer",
      "url": "https://www.sueddeutsche.de/raetsel/aktuell/str8ts/",
      "image_url": "https://www.sueddeutsche.de/2025/04/11/75a4b485-76c2-4e57-8e26-254aaa3171d4.png?rect=0,0,832,624&width=217&fm=png&q=60"
    },
    {
      "title": "Buchstabenring: täglich neu:Bilden Sie Wörter – je weniger, desto besser",
      "url": "https://www.sueddeutsche.de/raetsel/aktuell/buchstabenring/",
      "image_url": "https://www.sueddeutsche.de/2024/03/18/53356549-9d8e-4c7a-a2e3-8d53c738d1fc.png?rect=0,0,832,624&width=217&fm=png&q=60"
    },
    {
      "title": "Futoshiki: jeden Tag anders:Füllen Sie das Quadrat – so, dass alles passt",
      "url": "https://www.sueddeutsche.de/raetsel/aktuell/futoshiki/",
      "image_url": "https://www.sueddeutsche.de/2024/03/18/42756151-dcb3-4eb0-bf1d-6b0c8f1d1e97.png?rect=0,0,832,624&width=217&fm=png&q=60"
    },
    {
      "title": "Quartett: Mittwoch & Samstag:Vier Bilder, eine Gemeinsamkeit – welche?",
      "url": "https://www.sueddeutsche.de/raetsel/aktuell/quartett/",
      "image_url": "https://www.sueddeutsche.de/2024/03/18/9bf7b4f6-c393-4613-867d-7aaac7e1de20.png?rect=0,0,832,624&width=217&fm=png&q=60"
    },
    {
      "title": "Schach-Rätsel: täglich neu:Sie sind am Zug – mit Tipps vom Großmeister",
      "url": "https://www.sueddeutsche.de/raetsel/aktuell/schach/",
      "image_url": "https://www.sueddeutsche.de/2024/03/18/ff819e61-ef13-46ce-b5e6-7fd5351b6a4d.png?rect=0,0,832,624&width=217&fm=png&q=60"
    },
    {
      "title": "Fünf Texte aus „The Atlantic“ im Original:Trump verzettelt sich. Der kaputte Berufseinstieg. Glück lernen. Und mehr.",
      "url": "https://www.sueddeutsche.de/projekte/artikel/verlag/5-stories-from-the-atlantic-e683752/",
      "image_url": "https://www.sueddeutsche.de/2025/05/22/6f47d168-4db3-4f69-b02a-86454f8d6f4a.jpeg?rect=500,0,3000,2250&width=217&fm=jpeg&q=60"
    },
    {
      "title": "USA:Trump verzettelt sich",
      "url": "https://www.sueddeutsche.de/projekte/artikel/politik/trump-s-affordability-weave-e608143/",
      "image_url": "https://www.sueddeutsche.de/2025/12/18/b0315e35-4022-4eba-8fd8-d04abae109a3.jpg?rect=53,0,893,670&width=217&fm=jpeg&q=60"
    },
    {
      "title": "Karriere:Der kapputte Berufseinstieg",
      "url": "https://www.sueddeutsche.de/projekte/artikel/gesellschaft/the-entry-level-hiring-process-is-breaking-down-e028440/",
      "image_url": "https://www.sueddeutsche.de/2025/12/18/d3b25ac6-31df-48e6-86e5-4f4a84da4da6.jpg?rect=496,0,2981,2236&width=217&fm=jpeg&q=60"
    },
    {
      "title": "USA:Amerikas längster Abschiedsbrief",
      "url": "https://www.sueddeutsche.de/projekte/artikel/politik/the-longest-suicide-note-in-american-history-e007466/",
      "image_url": "https://www.sueddeutsche.de/2025/12/18/bc2335d7-5501-4e52-a09a-10218247193f.jpg?rect=222,0,3556,2667&width=217&fm=jpeg&q=60"
    },
    {
      "title": "Psychologie:Glück lernen",
      "url": "https://www.sueddeutsche.de/projekte/artikel/gesellschaft/how-to-be-happy-like-thomas-aquinas-e787842/",
      "image_url": "https://www.sueddeutsche.de/2025/12/18/9705179d-4376-4395-8ef9-c11b8930dd6a.jpg?rect=84,0,3536,2652&width=217&fm=jpeg&q=60"
    },
    {
      "title": "Populismus:Der Aufstand gegen Denk-Eliten",
      "url": "https://www.sueddeutsche.de/projekte/artikel/politik/the-populist-revolt-against-cognitive-elites-e950864/",
      "image_url": "https://www.sueddeutsche.de/2025/12/18/7be2251d-c273-4fad-86d5-4145c404416b.jpg?rect=0,78,4000,3000&width=217&fm=jpeg&q=60"
    },
    {
      "title": "USA:Trump Is Making the Same Mistake as Biden",
      "url": "https://www.sueddeutsche.de/projekte/artikel/politik/trump-is-making-the-same-mistake-as-biden-e574898/",
      "image_url": "https://www.sueddeutsche.de/2025/12/11/2f64c231-819d-4a70-b722-051073e389f1.jpg?rect=292,110,1580,1185&width=217&fm=jpeg&q=60"
    },
    {
      "title": "USA:What Explains Trump’s Aggression Toward Venezuela? Who Knows.",
      "url": "https://www.sueddeutsche.de/projekte/artikel/politik/what-explains-trump-s-aggression-toward-venezuela-who-knows-e524224/",
      "image_url": "https://www.sueddeutsche.de/2025/12/11/3c768a9c-c4c1-43e5-989a-f045b17d8992.jpg?rect=618,119,2775,2082&width=217&fm=jpeg&q=60"
    },
    {
      "title": "Zeitgeit:Make Culture Weird Again",
      "url": "https://www.sueddeutsche.de/projekte/artikel/kultur/make-culture-weird-again-e849138/",
      "image_url": "https://www.sueddeutsche.de/2025/12/11/8b7c9443-00e8-4deb-b7c7-3470e7d43112.jpg?rect=529,114,2872,2155&width=217&fm=jpeg&q=60"
    },
    {
      "title": "Donald Trump:President Piggy",
      "url": "https://www.sueddeutsche.de/projekte/artikel/gesellschaft/president-piggy-e459826/",
      "image_url": "https://www.sueddeutsche.de/2025/11/27/82121793-8f31-4de7-947e-a5e23fec6a19.jpg?rect=222,0,3556,2667&width=217&fm=jpeg&q=60"
    },
    {
      "title": "USA:(Some) MAGA Girls Just Wanna Have Fun",
      "url": "https://www.sueddeutsche.de/projekte/artikel/politik/some-maga-girls-just-wanna-have-fun-e538822/",
      "image_url": "https://www.sueddeutsche.de/2025/11/27/127d4c6c-3964-43a5-9aa5-1038b4213ddd.jpg?rect=128,0,3169,2377&width=217&fm=jpeg&q=60"
    },
    {
      "title": "Psychologie:Das Erholungs-Protokoll",
      "url": "https://www.sueddeutsche.de/projekte/artikel/gesellschaft/an-evening-ritual-to-realize-a-happier-life-e724323/",
      "image_url": "https://www.sueddeutsche.de/2025/11/20/00a4e223-180d-446e-9c8c-402471a1042d.jpg?rect=220,0,3558,2669&width=217&fm=jpeg&q=60"
    },
    {
      "title": "Gastbeitrag von Nancy Pelosi:Amerika ist groß, wenn Amerika gut ist",
      "url": "https://www.sueddeutsche.de/projekte/artikel/politik/america-is-great-when-america-is-good-e725148/",
      "image_url": "https://www.sueddeutsche.de/2025/11/13/d2cfea2b-2c03-461d-8742-9c6a39f61a6f.jpg?rect=205,0,2830,2123&width=217&fm=jpeg&q=60"
    },
    {
      "title": "USA:Die Mafia Präsidentschaft",
      "url": "https://www.sueddeutsche.de/projekte/artikel/politik/the-mafia-presidency-e009367/",
      "image_url": "https://www.sueddeutsche.de/2025/11/13/e6779c51-2a31-4219-88a8-b1103bc35abd.jpg?rect=279,0,1802,1352&width=217&fm=jpeg&q=60"
    },
    {
      "title": "Kultur:Nein, Frauen sind nicht das Problem",
      "url": "https://www.sueddeutsche.de/projekte/artikel/gesellschaft/no-women-aren-t-the-problem-e320621/",
      "image_url": "https://www.sueddeutsche.de/2025/11/13/cf85de72-e2de-4ab3-9c76-80c9eca9690d.jpg?rect=222,0,3556,2667&width=217&fm=jpeg&q=60"
    },
    {
      "title": "Beziehung:Drei Regeln für eine glückliche Ehe",
      "url": "https://www.sueddeutsche.de/projekte/artikel/gesellschaft/three-rules-for-a-lasting-happy-marriage-e149085/",
      "image_url": "https://www.sueddeutsche.de/2025/11/13/547e8b88-af35-4c74-a9e1-f241a7f8bb24.jpg?rect=278,0,3442,2582&width=217&fm=jpeg&q=60"
    },
    {
      "title": "USA:Der Kindergarten im Weißen Haus",
      "url": "https://www.sueddeutsche.de/projekte/artikel/politik/a-confederacy-of-toddlers-e054370/",
      "image_url": "https://www.sueddeutsche.de/2025/11/06/9673fee0-b584-4781-abb5-75d0c3bbcb41.jpg?rect=158,0,3684,2763&width=217&fm=jpeg&q=60"
    },
    {
      "title": "Trump:Die Gefahr einer dritten Amtszeit",
      "url": "https://www.sueddeutsche.de/projekte/artikel/politik/the-solution-to-the-third-term-threat-e433180/",
      "image_url": "https://www.sueddeutsche.de/2025/11/06/ddbdf356-dda7-4665-a1b8-33f36f747384.jpg?rect=193,0,3111,2334&width=217&fm=jpeg&q=60"
    },
    {
      "title": "KI:Die Bestätigungsmaschinen",
      "url": "https://www.sueddeutsche.de/projekte/artikel/gesellschaft/the-validation-machines-e041957/",
      "image_url": "https://www.sueddeutsche.de/2025/11/06/3a56f008-2ca9-414a-9682-9b29a9b8bd1b.jpg?rect=0,168,4000,3000&width=217&fm=jpeg&q=60"
    },
    {
      "title": "Familie:Die bekiffte Gesellschaft",
      "url": "https://www.sueddeutsche.de/projekte/artikel/gesellschaft/the-lonely-new-vices-of-american-life-e252247/",
      "image_url": "https://www.sueddeutsche.de/2025/11/06/45460a67-0d7c-4ef3-bca3-ee2c5ff20513.jpg?rect=222,0,3556,2667&width=217&fm=jpeg&q=60"
    },
    {
      "title": "USA:The Government Is Closed. The President Is MIA.",
      "url": "https://www.sueddeutsche.de/projekte/artikel/politik/the-government-is-closed-the-president-is-mia-e176894/",
      "image_url": "https://www.sueddeutsche.de/2025/10/30/ffcbfe1c-96e7-41b7-a55b-c60e21764eb8.jpg?rect=353,0,3293,2470&width=217&fm=jpeg&q=60"
    },
    {
      "title": "KI:The Age of De-Skilling",
      "url": "https://www.sueddeutsche.de/projekte/artikel/gesellschaft/the-age-of-de-skilling-e490039/",
      "image_url": "https://www.sueddeutsche.de/2025/10/30/fe1b4a64-bb5e-4a3f-8b99-f63e5bac3de0.jpg?rect=278,0,3444,2583&width=217&fm=jpeg&q=60"
    },
    {
      "title": "Hochzeit:Bridesmaid Inflation",
      "url": "https://www.sueddeutsche.de/projekte/artikel/gesellschaft/bridesmaid-inflation-e005779/",
      "image_url": "https://www.sueddeutsche.de/2025/10/30/eb6928d4-02f4-44fd-803f-3852ce8f6c77.jpg?rect=594,0,2812,2109&width=217&fm=jpeg&q=60"
    },
    {
      "title": "USA:Steve Bannon and the Murderers and Hitmen Who Became His ‘Besties’",
      "url": "https://www.sueddeutsche.de/projekte/artikel/politik/steve-bannon-and-the-murderers-and-hitmen-who-became-his-besties-e216340/",
      "image_url": "https://www.sueddeutsche.de/2025/10/23/96219bec-82c8-46fc-99da-c2fc560064e5.jpg?rect=222,0,3556,2667&width=217&fm=jpeg&q=60"
    },
    {
      "title": "Gesellschaft und Verhalten:Can Gen Z Get Rid of Its iPhones?",
      "url": "https://www.sueddeutsche.de/projekte/artikel/gesellschaft/can-gen-z-get-rid-of-its-iphones-e176312/",
      "image_url": "https://www.sueddeutsche.de/2025/10/16/2cbc2e20-34dc-4d03-bb85-beb3e521bc71.jpg?rect=480,0,2880,2160&width=217&fm=jpeg&q=60"
    },
    {
      "title": "Kopf und Körper:The Mind-Altering Effect of a Good Workout Routine",
      "url": "https://www.sueddeutsche.de/projekte/artikel/gesellschaft/the-mind-altering-effect-of-a-good-workout-routine-e109407/",
      "image_url": "https://www.sueddeutsche.de/2025/10/09/98769e13-9262-4c31-9cb1-d98b9e670b58.jpg?rect=195,0,3135,2352&width=217&fm=jpeg&q=60"
    },
    {
      "title": "Gesellschaft:America’s Zombie Democracy",
      "url": "https://www.sueddeutsche.de/projekte/artikel/politik/america-s-zombie-democracy-e946501/",
      "image_url": "https://www.sueddeutsche.de/2025/10/02/dddb6bb3-efaf-4481-9cfe-e85d99f2aacb.jpg?rect=160,0,2398,1799&width=217&fm=jpeg&q=60"
    },
    {
      "title": "Trumponomics:The Era of Step-on-a-Rake Capitalism",
      "url": "https://www.sueddeutsche.de/projekte/artikel/politik/the-era-of-step-on-a-rake-capitalism-e524118/",
      "image_url": "https://www.sueddeutsche.de/2025/10/02/be6fdfae-9c55-4234-b305-acfa63379cea.jpg?rect=252,0,3496,2622&width=217&fm=jpeg&q=60"
    },
    {
      "title": "Kamala Harris über Biden:Democrats Are Still Debating Joe Biden’s Decision to Run",
      "url": "https://www.sueddeutsche.de/projekte/artikel/politik/democrats-are-still-debating-joe-biden-s-decision-to-run-e802848/",
      "image_url": "https://www.sueddeutsche.de/2025/09/18/795e1d5c-2d3a-4027-9397-5656dc35d4ac.jpg?rect=222,0,3556,2667&width=217&fm=jpeg&q=60"
    },
    {
      "title": "Besser in den Tag starten:Six Ways to Start Early and Lift Your Mood",
      "url": "https://www.sueddeutsche.de/projekte/artikel/gesellschaft/six-ways-to-start-early-and-lift-your-mood-e226571/",
      "image_url": "https://www.sueddeutsche.de/2025/09/18/dc01e43d-809e-4d3f-afd2-c1f78fd477f7.jpg?rect=133,0,3733,2800&width=217&fm=jpeg&q=60"
    },
    {
      "title": "Familie:The Marriage Effect",
      "url": "https://www.sueddeutsche.de/projekte/artikel/gesellschaft/the-marriage-effect-e573725/",
      "image_url": "https://www.sueddeutsche.de/2025/09/04/0d0ac733-5392-424c-a63c-4eeafdcca15a.jpg?rect=256,0,2833,2125&width=217&fm=jpeg&q=60"
    },
    {
      "title": "Inkompetenz:Trump’s Unforgivable Sin",
      "url": "https://www.sueddeutsche.de/projekte/artikel/politik/trump-s-unforgivable-sin-e442313/",
      "image_url": "https://www.sueddeutsche.de/2025/08/14/d20d6408-a496-4dd8-9253-629845593f5c.jpg?rect=222,0,3556,2667&width=217&fm=jpeg&q=60"
    },
    {
      "title": "USA:Why Trump Can’t Make the Epstein Story Go Away",
      "url": "https://www.sueddeutsche.de/projekte/artikel/politik/why-trump-can-t-make-the-epstein-story-go-away-e631214/",
      "image_url": "https://www.sueddeutsche.de/2025/07/17/2411121e-8f97-4519-b9cf-70e9fa55d9d0.jpg?rect=204,0,3275,2457&width=217&fm=jpeg&q=60"
    },
    {
      "title": "Eine Liebeserklärung:Pamela Anderson Forever",
      "url": "https://www.sueddeutsche.de/projekte/artikel/gesellschaft/pamela-anderson-forever-e121528/",
      "image_url": "https://www.sueddeutsche.de/2025/07/17/b528a4b1-06c4-4741-b7cc-bfcdc2109c73.jpg?rect=222,0,3556,2667&width=217&fm=jpeg&q=60"
    },
    {
      "title": "Moral und Philosophie:Why Do So Many People Think That Trump Is Good?",
      "url": "https://www.sueddeutsche.de/projekte/artikel/politik/why-do-so-many-people-think-that-trump-is-good-e213853/",
      "image_url": "https://www.sueddeutsche.de/2025/07/10/c3774473-8288-4bac-85e5-19a9e12be95f.jpg?rect=213,0,3509,2632&width=217&fm=jpeg&q=60"
    },
    {
      "title": "Politik:Where Is Barack Obama?",
      "url": "https://www.sueddeutsche.de/projekte/artikel/politik/where-is-barack-obama-e458422/",
      "image_url": "https://www.sueddeutsche.de/2025/06/12/4b274f7a-1688-46c8-82be-0d8954c0888e.jpeg?rect=366,0,3268,2451&width=217&fm=jpeg&q=60"
    },
    {
      "title": "Ein Gespräch mit Donald Trump:‘I Run the Country and the World’",
      "url": "https://www.sueddeutsche.de/projekte/artikel/politik/trump-i-run-the-country-and-the-world-e153574/",
      "image_url": "https://www.sueddeutsche.de/2025/05/23/95a22441-ffdc-431e-97d8-f9b4791764b9.jpeg?rect=166,0,2666,2000&width=217&fm=jpeg&q=60"
    },
    {
      "title": "Der US-Vize-Präsident im Porträt:The Talented Mr. Vance",
      "url": "https://www.sueddeutsche.de/projekte/artikel/politik/the-talented-mr-vance-e342287/",
      "image_url": "https://www.sueddeutsche.de/2025/05/23/3be81036-8120-418c-95a7-0e543b6a96e2.jpeg?rect=128,0,2053,1540&width=217&fm=jpeg&q=60"
    },
    {
      "title": "SZ PlusExklusivPodcast der Süddeutschen Zeitung und Auf Ex Productions:Die Jägerin – Staffel 2",
      "url": "https://www.sueddeutsche.de/projekte/artikel/panorama/jaegerin-staffel-2-fortsetzung-mord-auf-ex-bartsch-schuetze-e577412/",
      "image_url": "https://www.sueddeutsche.de/2025/12/17/941ab44a-8ed2-4acb-a963-aafb11b401cd.jpg?rect=320,0,1920,1440&width=217&fm=jpeg&q=60"
    },
    {
      "title": "SZ PlusEine Podcast-Serie der Süddeutschen Zeitung:Greta - Die Geschichte einer Eskalation",
      "url": "https://www.sueddeutsche.de/projekte/artikel/gesellschaft/greta-thunberg-fridays-for-future-gaza-israel-podcast-klimaaktivistin-e295746/",
      "image_url": "https://www.sueddeutsche.de/2025/10/23/d64d12b0-8822-4712-b72f-99cd05a06a3d.jpg?rect=456,0,2736,2052&width=217&fm=jpeg&q=60"
    },
    {
      "title": "SZ PlusInterview-Podcast:Alles Liebe",
      "url": "https://www.sueddeutsche.de/projekte/artikel/magazin/podcast-interview-alles-liebe-e075693/",
      "image_url": "https://www.sueddeutsche.de/2025/10/01/0e6de08d-a006-4e4b-ba2a-ceea8f0acf90.jpg?rect=320,0,1920,1440&width=217&fm=jpeg&q=60"
    },
    {
      "title": "SZ PlusDer Kampf um den seltensten Vogel der Welt:Der Papageienkönig",
      "url": "https://www.sueddeutsche.de/projekte/artikel/panorama/podcast-spix-ara-papageienkoenig-martin-guth-artenschutz-e688038/",
      "image_url": "https://www.sueddeutsche.de/2025/05/28/f78fc414-762b-4f6e-a2c6-e917576f316c.png?rect=456,0,2736,2052&width=217&fm=png&q=60"
    },
    {
      "title": "SZ PlusInterviewpodcast mit Ronen Steinke:Ist das gerecht?",
      "url": "https://www.sueddeutsche.de/thema/Ist_das_gerecht%3F",
      "image_url": "https://www.sueddeutsche.de/2025/05/21/62cbd234-f61c-49b2-af6c-761a110d6199.jpeg?rect=0,0,1600,1200&width=217&fm=jpeg&q=60"
    },
    {
      "title": "SZ PlusEin Leben vor Gericht:Am Abgrund",
      "url": "https://www.sueddeutsche.de/projekte/artikel/panorama/kriminalfaelle-podcast-gerichtsprozesse-justiz-am-abgrund-e522163/",
      "image_url": "https://www.sueddeutsche.de/2025/04/17/e5bd7b12-95ca-4029-bda5-0fc9c20d573c.jpeg?rect=456,0,2736,2052&width=217&fm=jpeg&q=60"
    },
    {
      "title": "SZ PlusÜber die Fragen unserer Zeit:In aller Ruhe",
      "url": "https://www.sueddeutsche.de/thema/In_aller_Ruhe",
      "image_url": "https://www.sueddeutsche.de/2025/05/16/5975ec79-c538-4604-92bc-2ea592e31dca.jpeg?rect=0,0,1600,1200&width=217&fm=jpeg&q=60"
    },
    {
      "title": "SZ PlusZwei Korrespondenten beidseits des Atlantiks:Deutsch-Amerikanische Freundschaft",
      "url": "https://www.sueddeutsche.de/thema/Deutsch-Amerikanische_Freundschaft",
      "image_url": "https://www.sueddeutsche.de/2025/03/12/a28bfb7b-8656-409b-9321-5334e186e0c2.jpeg?rect=0,0,1600,1200&width=217&fm=jpeg&q=60"
    },
    {
      "title": "SZ PlusAuf der Suche nach einer geheimen Liebe:Die Kiste",
      "url": "https://www.sueddeutsche.de/projekte/artikel/panorama/verbotene-liebesbeziehung-alte-kiste-nazi-deutschland-china-podcast-e264211/",
      "image_url": "https://www.sueddeutsche.de/2025/03/12/48f87fb9-2c4f-46e7-93b1-1aab40aa382f.jpeg?rect=0,0,1600,1200&width=217&fm=jpeg&q=60"
    },
    {
      "title": "SZ PlusDie wirklich wahre Geschichte des größten Lügners von Amerika:Old Man Trump",
      "url": "https://www.sueddeutsche.de/projekte/artikel/politik/podcast-donald-trump-luegner-amerika-wahrheit-us-wahl-2024-e958028/",
      "image_url": "https://www.sueddeutsche.de/2025/03/12/ed8a8608-32d7-451f-b9ee-dafb52372934.jpeg?rect=0,0,1600,1200&width=217&fm=jpeg&q=60"
    },
    {
      "title": "SZ PlusExklusivPodcast:Die Jagd nach der schnellsten Frau der Welt",
      "url": "https://www.sueddeutsche.de/projekte/artikel/sport/podcast-weltrekord-florence-griffith-joyner-100-meter-olympia-leichtathletik-flojo-e984143/",
      "image_url": "https://www.sueddeutsche.de/2024/07/18/6dba6429-c4c2-41cc-ab8c-51ae89c96543.png?rect=456,0,2736,2052&width=217&fm=png&q=60"
    },
    {
      "title": "SZ PlusDas System Rammstein und der Machtmissbrauch in der Musik:Feuerzone",
      "url": "https://www.sueddeutsche.de/projekte/artikel/kultur/podcast-rammstein-feuerzone-lindemann-e820426",
      "image_url": "https://www.sueddeutsche.de/2025/03/12/29f13f5b-a30d-4763-9b54-e31453703b04.jpeg?rect=0,0,1600,1200&width=217&fm=jpeg&q=60"
    },
    {
      "title": "SZ PlusSZ MagazinDer Exorzist aus dem Internet:Dämon",
      "url": "https://www.sueddeutsche.de/projekte/artikel/magazin/podcast-daemon-exorzist-e871010/",
      "image_url": "https://www.sueddeutsche.de/2025/03/12/4b8004d1-8b71-40e0-8266-1418aa985cb6.jpeg?rect=0,0,1600,1200&width=217&fm=jpeg&q=60"
    },
    {
      "title": "SZ PlusExklusivSein Kampf um die Macht:Söders Endspiel",
      "url": "https://www.sueddeutsche.de/projekte/artikel/politik/podcast-soeder-wahlkampf-kanzler-bayern-landtagswahl-e234790/",
      "image_url": "https://www.sueddeutsche.de/2025/03/12/e614d189-0f71-4bfe-9708-6ccff7f31e45.jpeg?rect=0,0,1600,1200&width=217&fm=jpeg&q=60"
    },
    {
      "title": "SZ PlusDie neue Lust am Untergang:German Angst",
      "url": "https://www.sueddeutsche.de/projekte/artikel/politik/german-angst-podcast-e989005/",
      "image_url": "https://www.sueddeutsche.de/2025/03/12/d48f3133-8e75-42b2-9601-1a60370c975f.jpeg?rect=0,0,1600,1200&width=217&fm=jpeg&q=60"
    },
    {
      "title": "SZ PlusMeine Suche nach einem Phantom:Wer ist Joni?",
      "url": "https://www.sueddeutsche.de/projekte/artikel/gesellschaft/podcast-missbrauch-kriminalitaet-internet-e315467/",
      "image_url": "https://www.sueddeutsche.de/2025/03/12/ad18140b-96bf-4a50-9822-7aaf264fa208.jpeg?rect=0,0,1600,1200&width=217&fm=jpeg&q=60"
    },
    {
      "title": "SZ PlusAuf- und Abstieg von Alice Schwarzer:Who the f*** is Alice?",
      "url": "https://www.sueddeutsche.de/projekte/artikel/gesellschaft/alice-schwarzer-podcast-feminismus-e267062/",
      "image_url": "https://www.sueddeutsche.de/2025/03/12/76d2fc74-5053-49ba-ae88-233e57015118.jpeg?rect=0,0,1600,1200&width=217&fm=jpeg&q=60"
    },
    {
      "title": "SZ PlusEin unglaublicher Fall:Die Mafiaprinzessin",
      "url": "https://projekte.sueddeutsche.de/artikel/medien/die-mafiaprinzessin-ein-podcast-des-sz-magazins-e745821/",
      "image_url": "https://www.sueddeutsche.de/2025/03/12/3e2e028b-bbdc-4e24-bcad-cfe95ad00218.jpeg?rect=0,0,1600,1200&width=217&fm=jpeg&q=60"
    },
    {
      "title": "SZ PlusEinbruch ins Grüne Gewölbe:Die Kunst zu stehlen",
      "url": "https://www.sueddeutsche.de/projekte/artikel/panorama/podcast-gruenes-gewoelbe-true-crime-e159845/",
      "image_url": "https://www.sueddeutsche.de/2025/03/12/50b6d544-a2ce-4b25-a38c-74b062d99af3.jpeg?rect=0,0,1600,1200&width=217&fm=jpeg&q=60"
    },
    {
      "title": "SZ PlusSexualisierte Gewalt an Kindern:Vor aller Augen",
      "url": "https://www.sueddeutsche.de/projekte/artikel/politik/vor-aller-augen-podcast-serie-ueber-sexuelle-gewalt-an-kindern-e000844/",
      "image_url": "https://www.sueddeutsche.de/2025/03/12/b85cac5b-bcf0-4cc7-b002-bebb2eff4aa9.jpeg?rect=0,0,1600,1200&width=217&fm=jpeg&q=60"
    },
    {
      "title": "SZ PlusDie Löwen, die Arena und das Geld:Inside 1860",
      "url": "https://projekte.sueddeutsche.de/artikel/medien/inside-1860-ein-podcast-ueber-den-tsv-1860-muenchen-e426953/",
      "image_url": "https://www.sueddeutsche.de/2025/03/12/470e03e5-fe53-4e57-abd4-dc584bdf698d.jpeg?rect=0,0,1600,1200&width=217&fm=jpeg&q=60"
    },
    {
      "title": "SZ PlusMein Leben nach dem Amoklauf von Erfurt:71 Schüsse",
      "url": "https://www.sueddeutsche.de/projekte/artikel/kultur/71-schuesse-mein-leben-nach-dem-amoklauf-von-erfurt-ein-podcast-e242927/",
      "image_url": "https://www.sueddeutsche.de/2025/03/12/35395d4b-ca2e-46f3-8ed0-4fa3e1a0e5cb.jpeg?rect=0,0,1600,1200&width=217&fm=jpeg&q=60"
    },
    {
      "title": "SZ PlusDie Ibiza-Affäre in Österreich:Going to Ibiza",
      "url": "https://projekte.sueddeutsche.de/artikel/medien/artikel-e370761/",
      "image_url": "https://www.sueddeutsche.de/2025/03/12/d8b3cf06-36d2-4eb5-9212-b6a33e1dcef0.jpeg?rect=0,0,1600,1200&width=217&fm=jpeg&q=60"
    },
    {
      "title": "SZ PlusNSU und rechter Terror:Deutsche Abgründe",
      "url": "https://projekte.sueddeutsche.de/artikel/medien/nsu-prozess-deutsche-abgruende-podcast-serie-der-sz-e669669/",
      "image_url": "https://www.sueddeutsche.de/2025/03/12/da5a17a4-e5be-4b19-8d2a-436952bbd289.jpeg?rect=0,0,1600,1200&width=217&fm=jpeg&q=60"
    },
    {
      "title": "Ausstellung im Allgäu:Wie aus „Lego-Fieber“ eine ganz eigene Welt wurde",
      "teaser": "Tobias Schön hat im Galeria in Memmingen über die Jahre so viel Lego gekauft, dass ihn irgendwann die Verkäufer angesprochen haben. Jetzt hat der seine eigene Ausstellung, im Kaufhaus, auf 200 Quadratmetern – und die Besucher sind begeistert.",
      "url": "https://www.sueddeutsche.de/bayern/lego-welt-memmingen-ausstellung-allgaeu-steinekeller-li.3355395",
      "image_url": "https://www.sueddeutsche.de/2025/12/16/8327db1f-c491-4f73-b58c-af65b99c0231.jpg?rect=0,375,4000,2250&width=630&fm=jpeg&q=60"
    },
    {
      "title": "Unglück am Laubeneck:14-Jähriger stürzt tödlich am Berg",
      "url": "https://www.sueddeutsche.de/bayern/unterammergau-bayern-laubeneck-berg-sturz-14-jaehriger-tod-li.3360721",
      "image_url": "https://www.sueddeutsche.de/2025/04/08/5d5c3ae6-a5cf-44a1-8d39-5a7e2a9a4c4e.jpeg?rect=276,0,3448,2586&width=217&fm=jpeg&q=60"
    },
    {
      "title": "Migration:Im Jahr 2025 weniger unerlaubte Einreisen nach Bayern",
      "url": "https://www.sueddeutsche.de/bayern/bayern-migration-einreise-bundespolizei-li.3360567",
      "image_url": "https://www.sueddeutsche.de/2022/06/13/53c2c6b1-aaeb-4f83-b385-d30db04d19fa.jpeg?rect=75,0,1200,900&width=217&fm=jpeg&q=60"
    },
    {
      "title": "Friedensgespräche in Florida:Trump und Selenskij sprechen von Fortschritten, bleiben aber vage",
      "teaser": "Die Präsidenten der USA und der Ukraine sagen, sie hätten sich in umstrittenen Punkten angenähert. Trump telefonierte am Sonntag aber nach eigenen Angaben auch zweieinhalb Stunden mit Putin.",
      "url": "https://www.sueddeutsche.de/politik/trump-selenskij-friedensprozess-mar-a-lago-li.3360347",
      "image_url": "https://www.sueddeutsche.de/2025/12/29/c8b85748-a01e-46cb-b8ca-48a7ee545d2f.jpg?rect=223,581,3636,2045&width=630&fm=jpeg&q=60"
    },
    {
      "title": "SZ-Podcast „Auf den Punkt“:2025: Was wurde aus ICE-Deportationen, Gaza-Kriegsverbrechen und Russlands Eroberungen?",
      "url": "https://www.sueddeutsche.de/politik/2025-jahresrueckblick-li.3357235",
      "image_url": "https://www.sueddeutsche.de/2025/03/12/4d031366-ad93-4b81-89dc-aa57357f2531.png?rect=400,0,2400,1800&width=217&fm=png&q=60"
    },
    {
      "title": "SZ PlusEU:Die Brandmauer fällt, und niemand schaut hin",
      "url": "https://www.sueddeutsche.de/politik/europaparlament-brandmauer-sozialdemokraten-weber-li.3358729",
      "image_url": "https://www.sueddeutsche.de/2025/12/26/a0641c7b-3fcb-458d-a8a5-5767c50b5a70.jpg?rect=174,0,2731,2048&width=217&fm=jpeg&q=60"
    },
    {
      "title": "Altersvorsorge:Ratingagentur: Rentenreform nötig für AAA-Rating Deutschlands",
      "teaser": "Die Ratingagentur Scope mahnt Deutschland zu einer großen Rentenreform, um die Kreditwürdigkeit des Landes auf Topniveau zu halten. Auch viele Bürger sehen das einer Umfrage zufolge ähnlich.",
      "url": "https://www.sueddeutsche.de/wirtschaft/ratingagentur-rentenreform-deutschland-li.3360313",
      "image_url": "https://www.sueddeutsche.de/2025/11/18/cd16950d-f3f1-4725-b50d-fca022e8f656.jpg?rect=0,209,4000,2250&width=630&fm=jpeg&q=60"
    },
    {
      "title": "Cartoon:Meissners Strategen",
      "url": "https://www.sueddeutsche.de/wirtschaft/cartoon-meissners-strategen-li.3360257",
      "image_url": "https://www.sueddeutsche.de/2025/12/28/cf60bc29-55de-433b-ab51-b637923a51dd.jpg?rect=561,0,2879,2159&width=217&fm=jpeg&q=60"
    },
    {
      "title": "SZ PlusSigna-Pleite:René Benko sitzt in Haft – womöglich nicht mehr lange",
      "url": "https://www.sueddeutsche.de/wirtschaft/rene-benko-untersuchungshaft-ermittlungen-wien-li.3335511",
      "image_url": "https://www.sueddeutsche.de/2025/12/23/5ac89e86-db93-4f5e-a7c6-4a8d444ccb6a.jpg?rect=113,0,1821,1366&width=217&fm=jpeg&q=60"
    },
    {
      "title": "Cartoonfigur:Die Rückkehr der Diddl-Maus",
      "teaser": "Die Diddl-Maus, das Kult-Objekt der Neunziger, lebt wieder. Auf Bleistiften, Notizblöcken und als Plüschtier – aber nur in Frankreich. Wer sind die Leute, die dort jetzt die Läden leer kaufen?",
      "url": "https://www.sueddeutsche.de/panorama/diddl-maus-comeback-li.3353072",
      "image_url": "https://www.sueddeutsche.de/2025/12/22/75e12b81-692b-4c23-a56e-828c1f9e0d01.jpg?rect=0,0,4000,2250&width=630&fm=jpeg&q=60"
    },
    {
      "title": "SZ PlusCold Cases:„Auch diese Opfer haben eine Stimme“",
      "url": "https://www.sueddeutsche.de/panorama/cold-case-uni-koeln-studenten-li.3339890",
      "image_url": "https://www.sueddeutsche.de/2025/12/23/27415563-7cc9-4af4-9108-37f0dbb095bb.jpg?rect=382,0,3436,2577&width=217&fm=jpeg&q=60"
    },
    {
      "title": "SZ Plus„Gender Disappointment“:„Babys sind doch süß. Es sei denn, es sind Jungen“",
      "url": "https://www.sueddeutsche.de/panorama/gender-disappointment-enttaeuschung-geschlecht-kindes-li.3339998",
      "image_url": "https://www.sueddeutsche.de/2025/12/10/6d2a39a2-f1af-4e5e-909d-775c6e698ea9.jpg?rect=367,0,3556,2667&width=217&fm=jpeg&q=60"
    },
    {
      "title": "SZ-Podcast „Das Thema“:„Das Krankenhaus des Todes“: Folter in Syrien unter Assad",
      "url": "https://www.sueddeutsche.de/politik/syrien-assad-folter-damascus-dossier-recherche-li.3347144",
      "image_url": "https://www.sueddeutsche.de/2025/03/12/6ba371d7-d4f1-434d-8285-1596ecc4874d.png?rect=400,0,2400,1800&width=217&fm=png&q=60"
    },
    {
      "title": "SZ Plus„Ist das gerecht?“ – Interview-Podcast mit Ronen Steinke:„Wir sind ein Gefäß von Subjektivitäten“",
      "url": "https://www.sueddeutsche.de/meinung/berichterstattung-kurt-kister-podcast-li.3355141",
      "image_url": "https://www.sueddeutsche.de/2025/12/17/10b21dc1-f846-48cf-9cde-359a5c983df8.jpg?rect=178,0,1799,1349&width=217&fm=jpeg&q=60"
    },
    {
      "title": "Podcast „Und nun zum Sport“:WM 2026: „Der Fußball hat sich bis zum Finale Donald Trump unterworfen“",
      "url": "https://www.sueddeutsche.de/sport/wm-2026-trump-infantino-auslosung-nationalteam-podcast-li.3350874",
      "image_url": "https://www.sueddeutsche.de/2025/03/12/0afd3006-5fca-48c8-8ca9-4264ae6d9876.jpeg?rect=320,0,1920,1440&width=217&fm=jpeg&q=60"
    },
    {
      "title": "SZ-Podcast München persönlich:Florian Brückner: „Vom Pumuckl kann man sich einiges abschauen“",
      "url": "https://www.sueddeutsche.de/muenchen/sz-podcast-muenchen-persoenlich-florian-brueckner-pumuckl-und-das-grosse-missverstaendnis-meister-eder-li.3331096",
      "image_url": "https://www.sueddeutsche.de/2025/10/27/05173ab7-351d-450a-91e8-f0e4d6ec0bf9.jpg?rect=0,0,3557,2668&width=217&fm=jpeg&q=60"
    },
    {
      "title": "SZ-Podcast „Deutsch-Amerikanische Freundschaft“:„Die Demokraten haben ihr Momentum selbst zerstört“",
      "url": "https://www.sueddeutsche.de/politik/podcast-demokraten-wagenknecht-partei-shutdown-deutsch-amerikanische-freundschaft-daf-li.3337367",
      "image_url": "https://www.sueddeutsche.de/2025/11/12/18b58fdd-3a6b-4b6a-9d73-6a5b392f36fe.jpg?rect=300,0,1799,1349&width=217&fm=jpeg&q=60"
    },
    {
      "title": "SZ PlusEine Podcast-Serie der Süddeutschen Zeitung:Der Papageienkönig",
      "url": "https://www.sueddeutsche.de/projekte/artikel/panorama/podcast-spix-ara-papageienkoenig-martin-guth-artenschutz-e688038/",
      "image_url": "https://www.sueddeutsche.de/2025/05/28/f78fc414-762b-4f6e-a2c6-e917576f316c.png?rect=456,0,2736,2052&width=217&fm=png&q=60"
    },
    {
      "title": "SZ PlusPodcast-Serie:Die Kiste – Auf der Suche nach einer geheimen Liebe",
      "url": "https://www.sueddeutsche.de/projekte/artikel/panorama/verbotene-liebesbeziehung-alte-kiste-nazi-deutschland-china-podcast-e264211/",
      "image_url": "https://www.sueddeutsche.de/2024/12/05/61929c60-47d8-43bf-8ac8-6e009c2520dc.jpeg?rect=456,0,2736,2052&width=217&fm=jpeg&q=60"
    },
    {
      "title": "Podcast:Wirecard: 1,9 Milliarden Lügen (Staffel 4)",
      "url": "https://www.sueddeutsche.de/wirtschaft/podcast-wirecard-staffel4-1.6318625",
      "image_url": "https://www.sueddeutsche.de/2025/03/06/01939826-13fc-42e7-9058-0bd44e0386ed.jpeg?rect=179,0,1081,811&width=217&fm=jpeg&q=60"
    },
    {
      "title": "SZ PlusPodcast:Feuerzone - Das System Rammstein und der Machtmissbrauch in der Musik",
      "url": "https://www.sueddeutsche.de/projekte/artikel/kultur/podcast-rammstein-feuerzone-lindemann-e820426",
      "image_url": "https://www.sueddeutsche.de/2024/05/31/3b66ccf1-5ebd-43c6-9dd6-a1bd9ab707ba.jpeg?rect=320,0,1920,1440&width=217&fm=jpeg&q=60"
    },
    {
      "title": "SZ PlusPodcast:Old Man Trump – Die wirklich wahre Geschichte des größten Lügners von Amerika",
      "url": "https://www.sueddeutsche.de/projekte/artikel/politik/podcast-donald-trump-luegner-amerika-wahrheit-us-wahl-2024-e958028/",
      "image_url": "https://www.sueddeutsche.de/2024/10/10/25fe8c09-bb74-42eb-99ab-fcb8ea5a3aa1.jpeg?rect=320,0,1920,1440&width=217&fm=jpeg&q=60"
    },
    {
      "title": "SZ PlusExklusivPodcast:Die Jagd nach der schnellsten Frau der Welt",
      "url": "https://www.sueddeutsche.de/projekte/artikel/sport/podcast-weltrekord-florence-griffith-joyner-100-meter-olympia-leichtathletik-flojo-e984143/",
      "image_url": "https://www.sueddeutsche.de/2024/07/18/6dba6429-c4c2-41cc-ab8c-51ae89c96543.png?rect=456,0,2736,2052&width=217&fm=png&q=60"
    },
    {
      "title": "Momentaufnahmen im Dezember:Bilder des Tages",
      "teaser": "Schönes, Erschreckendes, Absurdes und ganz Alltägliches: Momentaufnahmen aus allen Ecken der Welt, laufend aktualisiert.",
      "url": "https://www.sueddeutsche.de/leben/momentaufnahmen-im-dezember-bilder-des-tages-li.3360352",
      "image_url": "https://www.sueddeutsche.de/2025/12/28/7f41d6d8-49e7-4107-bd14-fc5168637853.jpg?rect=5,436,3636,2045&width=630&fm=jpeg&q=60"
    },
    {
      "title": "SZ PlusEinmal im Leben:Zweimal Silvester feiern",
      "url": "https://www.sueddeutsche.de/projekte/artikel/reise/samoa-pazifik-silvester-apia-pago-pago-e059655/",
      "image_url": "https://www.sueddeutsche.de/2025/12/23/f7ce7f29-c19a-455f-bdc2-784710917604.jpg?rect=344,0,3556,2667&width=217&fm=jpeg&q=60"
    },
    {
      "title": "SZ PlusWohnen im Bunker:Idylle aus Beton",
      "url": "https://www.sueddeutsche.de/projekte/artikel/stil/bunker-hamburg-wohnen-design-interior-e957813/",
      "image_url": "https://www.sueddeutsche.de/2025/11/28/e4b127ea-2833-4a04-b2da-81e7432d3ca2.jpg?rect=1000,576,2337,1753&width=217&fm=jpeg&q=60"
    },
    {
      "title": "„Magic Moments“ 2024:Die besten Szenen des Kinojahres",
      "teaser": "Franz Kafka tollt nackt über eine Wiese, eine Atombombe fliegt und Revolutionäre bomben Zäune weg: die Lieblingsmomente der SZ-Kinokritiker 2025.",
      "url": "https://www.sueddeutsche.de/projekte/artikel/kultur/beste-filme-filme-des-jahres-2025-highlights-e571395/",
      "image_url": "https://www.sueddeutsche.de/2025/12/10/b03fee4e-e37c-4a81-9937-478350becb50.jpg?rect=0,156,3000,1687&width=630&fm=jpeg&q=60"
    },
    {
      "title": "SZ PlusLiteratur:Vergessen Sie alles, was Sie über die Welt wussten",
      "url": "https://www.sueddeutsche.de/kultur/cesar-aira-der-hase-roman-kritik-wann-literaturnobelpreis-li.3350000",
      "image_url": "https://www.sueddeutsche.de/2025/12/23/c4e6a8d2-a071-4fb6-87cf-e9d5bf9f0eda.jpg?rect=0,0,4000,3000&width=217&fm=jpeg&q=60"
    },
    {
      "title": "SZ PlusTrumpismus:Ein großes Jahr für die Autokraten-Show",
      "url": "https://www.sueddeutsche.de/kultur/trump-late-night-show-stephen-colbert-jimmy-kimmel-absetzen-washington-dc-li.3360127",
      "image_url": "https://www.sueddeutsche.de/2025/09/15/a08e3f78-c1da-41ff-9b1f-95467a04dc9d.jpg?rect=347,0,3111,2333&width=217&fm=jpeg&q=60"
    },
    {
      "title": "Talkshows:Das war das Talkshow-Jahr 2025",
      "teaser": "Wer war am häufigsten bei „Markus Lanz“ zu Gast, welche Themen wurden besprochen – und in welche Talkshow kommen eigentlich immer dieselben Gäste? Ein Jahresrückblick in Daten und Grafiken.",
      "url": "https://www.sueddeutsche.de/projekte/artikel/medien/talkshows-haeufigste-gaeste-datenanalyse-2025-lanz-maischberger-e434378/",
      "image_url": "https://www.sueddeutsche.de/2025/12/26/58b966a4-b896-429b-8a19-138ad2051cfd.png?rect=0,0,2078,1169&width=630&fm=png&q=60"
    },
    {
      "title": "SZ PlusSerie:Das Glück ist unsere größte Bedrohung",
      "url": "https://www.sueddeutsche.de/medien/pluribus-finale-letzte-folge-serie-apple-tv-rhea-seehorn-li.3358334",
      "image_url": "https://www.sueddeutsche.de/2025/12/23/bc92aea1-9b9b-4d48-ac6c-0f96831ec186.jpg?rect=823,0,2125,1594&width=217&fm=jpeg&q=60"
    },
    {
      "title": "SZ PlusKI und Journalismus:„Ein bisschen Kulturkampf“",
      "url": "https://www.sueddeutsche.de/medien/ulf-poschardt-welt-ki-instagram-anna-nina-li.3358339",
      "image_url": "https://www.sueddeutsche.de/2025/12/26/7e9dfd01-6358-4ec3-9b1d-0f9e30b9989c.jpg?rect=223,0,3555,2666&width=217&fm=jpeg&q=60"
    },
    {
      "title": "Wetter in Deutschland:So weit, so normal?",
      "teaser": "Ist es heute wärmer oder kälter als sonst um diese Zeit? Und welche Rolle spielt der Klimawandel? Finden Sie heraus, wie ungewöhnlich die Temperaturen aktuell in Ihrer Region sind.",
      "url": "https://www.sueddeutsche.de/projekte/artikel/wetter/hitze-temperatur-deutschland-vergleich-karte-e360874/",
      "image_url": "https://www.sueddeutsche.de/2025/07/02/6580e8a7-d35e-4a19-984f-0c7cf265e36b.png?rect=0,0,2078,1169&width=630&fm=png&q=60"
    },
    {
      "title": "SZ PlusWissenschaftspolitik:„Wir können gar nicht unpolitisch sein“",
      "url": "https://www.sueddeutsche.de/wissen/gerda-henkel-stiftung-foerderung-wissenschaft-fluechtlingshilfe-li.3357274",
      "image_url": "https://www.sueddeutsche.de/2025/12/21/1214064d-32e5-4524-8a0a-8f1073404887.jpg?rect=0,751,2008,1506&width=217&fm=jpeg&q=60"
    },
    {
      "title": "SZ PlusPsychologie:Wie wird man eigentlich weise?",
      "url": "https://www.sueddeutsche.de/wissen/weisheit-entscheidungen-lebenskompetenz-linden-psychiater-interview-li.3337269",
      "image_url": "https://www.sueddeutsche.de/2025/12/27/23487e91-3e45-41aa-85d6-56053ce9822f.jpg?rect=222,0,3556,2667&width=217&fm=jpeg&q=60"
    },
    {
      "title": "Dermatologie:Was die Sonnenbank mit der Haut macht",
      "teaser": "Häufige Besuche im Solarium lassen die Haut junger Menschen auf genetischer Ebene um Jahrzehnte altern, zeigt eine Studie. Rückgängig machen lässt sich das nicht.",
      "url": "https://www.sueddeutsche.de/gesundheit/solarium-haut-li.3360653",
      "image_url": "https://www.sueddeutsche.de/2025/12/29/cea8ab28-43a1-448a-8b0c-89b7e3f2248d.jpg?rect=0,104,600,337&width=630&fm=jpeg&q=60"
    },
    {
      "title": "Verhaltensbiologie:Auch Ratten kiffen gegen Stress",
      "url": "https://www.sueddeutsche.de/gesundheit/ratten-cannabis-stressbewaeltigung-tieren-li.3355175",
      "image_url": "https://www.sueddeutsche.de/2025/12/17/9d6dd628-a08b-4a5d-a8d5-c0cab02ff0f7.jpg?rect=123,0,1956,1467&width=217&fm=jpeg&q=60"
    },
    {
      "title": "Gesundheit:Woher der Winterspeck kommt",
      "url": "https://www.sueddeutsche.de/gesundheit/ursachen-winterspeck-gewichtszunahme-li.3358997",
      "image_url": "https://www.sueddeutsche.de/2025/12/23/0beeae1f-ad4e-4da8-85b3-ca6edf3cea7f.jpg?rect=223,0,3555,2666&width=217&fm=jpeg&q=60"
    },
    {
      "title": "Wintersport:Sanfter Ski fahren",
      "teaser": "Überlaufen, teuer, austauschbar: In den großen Urlaubsorten ist das Skifahren ein industriell betriebenes Geschäft, das auch in der Klimakrise möglichst reibungslos weiterlaufen soll. Das liegt auch an den Ansprüchen der Gäste. Ein Plädoyer für mehr Achtsamkeit und Spaß auf der Piste.",
      "url": "https://www.sueddeutsche.de/reise/ischgl-soelden-wintersport-eventindustrie-wandel-li.3337929",
      "image_url": "https://www.sueddeutsche.de/2025/12/18/5002ff22-d4ad-43e4-bf02-a3e8a0ce672a.jpg?rect=0,265,3300,1856&width=630&fm=jpeg&q=60"
    },
    {
      "title": "SZ PlusDem Geheimnis auf der Spur:Wer hat Santa Claus erfunden?",
      "url": "https://www.sueddeutsche.de/reise/weihnachtsmann-entstehung-santa-claus-li.3348504",
      "image_url": "https://www.sueddeutsche.de/2025/12/11/c252b7b3-fa4a-4d9f-86d8-b77fe1de6928.jpg?rect=0,0,2594,1946&width=217&fm=jpeg&q=60"
    },
    {
      "title": "SZ PlusWinterspaß in den Alpen:Guten Rutsch!",
      "url": "https://www.sueddeutsche.de/reise/winteraktivitaeten-salzburg-tirol-rosenheim-rodeln-driften-eislaufen-li.3344225",
      "image_url": "https://www.sueddeutsche.de/2025/12/22/dad4d1e7-507c-47fc-bd36-924e59ef4782.jpg?rect=0,1423,2661,1996&width=217&fm=jpeg&q=60"
    },
    {
      "title": "Mobilität:Das ändert sich im neuen Jahr",
      "teaser": "Sprit wird teurer, ebenso das Deutschlandticket. Es gibt aber auch steuerliche Entlastungen für Pendler. Was in Sachen Mobilität neu ist im Jahr 2026 – ein Überblick.",
      "url": "https://www.sueddeutsche.de/auto/aenderungen-2026-co-preis-deutschlandticket-pendlerpauschale-li.3317196",
      "image_url": "https://www.sueddeutsche.de/2025/09/24/b79227ae-fdd9-4583-9ab9-9514a3eb422c.jpg?rect=0,160,4000,2250&width=630&fm=jpeg&q=60"
    },
    {
      "title": "SZ PlusE-Bikes im Test:Gemütlicher Cruiser gegen sportlichen Alleskönner",
      "url": "https://www.sueddeutsche.de/projekte/artikel/auto/vergleich-bbf-pl625-kalkhoff-endeavour-test-e419084/",
      "image_url": "https://www.sueddeutsche.de/2025/11/10/5dd84be6-b098-43d0-9e23-34315b26d627.jpg?rect=196,0,1174,881&width=217&fm=jpeg&q=60"
    },
    {
      "title": "SZ PlusE-Mobilität:Fahrspaß ohne Andirndeln",
      "url": "https://www.sueddeutsche.de/auto/bmw-vision-ce-elektrofahrzeug-helm-schutzkleidung-li.3328126",
      "image_url": "https://www.sueddeutsche.de/2025/12/12/cc9f6c0e-e249-4e58-8358-712b988e2395.jpg?rect=498,0,3000,2250&width=217&fm=jpeg&q=60"
    },
    {
      "title": "Lebenserfahrung:Abschied vom Ich",
      "teaser": "Wie ist es, auf einmal ein Fremder zu sein? Unser Asien-Korrespondent hat im freundlichen Bangkok einiges über die Beschwerdekultur der Deutschen, die Unwucht der modernen Welt und vor allem über sich selbst gelernt.",
      "url": "https://www.sueddeutsche.de/leben/abschied-bangkok-erfahrungen-korrespondenten-li.3347487",
      "image_url": "https://www.sueddeutsche.de/2025/12/16/b9535966-03a9-4e2d-915e-a90c0c067bac.jpg?rect=0,1493,3646,2051&width=630&fm=jpeg&q=60"
    },
    {
      "title": "SZ PlusBestiarium – Von Tieren und Menschen:Das Foto, das sein Leben veränderte",
      "url": "https://www.sueddeutsche.de/projekte/artikel/gesellschaft/eisbaer-arktis-fotografie-e510149/",
      "image_url": "https://www.sueddeutsche.de/2025/12/17/7238f14e-ea13-4f50-8895-ff31310aae7c.jpg?rect=638,360,2722,2041&width=217&fm=jpeg&q=60"
    },
    {
      "title": "SZ Plus70 Jahre „Sissi“:Auf ewig Prinzessin",
      "url": "https://www.sueddeutsche.de/leben/historie-romy-schneider-sissi-elisabeth-von-oesterreich-fernsehen-li.3352970",
      "image_url": "https://www.sueddeutsche.de/2025/12/17/12c93e86-94cc-4624-8781-4fa3079a5794.jpg?rect=6,0,3488,2616&width=217&fm=jpeg&q=60"
    },
    {
      "title": "Interview:Auf ein Glas Champagner mit Vincent Chaperon",
      "teaser": "Wie ist es, als Kellermeister die Verantwortung für eines der berühmtesten Champagnerhäuser der Welt zu tragen? Begegnung mit einem Mann, der auch nüchtern von seinem Produkt berauscht ist.",
      "url": "https://www.sueddeutsche.de/stil/champagner-vincent-chaperon-blick-dom-perignon-li.3355989",
      "image_url": "https://www.sueddeutsche.de/2025/12/18/093fb2fa-a063-404b-a007-9af306e82ca1.jpg?rect=0,375,4000,2250&width=630&fm=jpeg&q=60"
    },
    {
      "title": "SZ PlusFestessen bei Spitzenköchen:\"Keiner erwartet zu Hause ein Sternemenü\"",
      "url": "https://www.sueddeutsche.de/projekte/artikel/stil/rezepte-spitzenkueche-alexander-herrmann-weihnachtsrezepte-thomas-buehner-e309244/",
      "image_url": "https://www.sueddeutsche.de/2025/12/19/3fb1b1ae-fc50-422e-9fc8-884d08014506.jpg?rect=375,0,2247,1686&width=217&fm=jpeg&q=60"
    },
    {
      "title": "Haben & Sein:Endspurt in den Schnee",
      "url": "https://www.sueddeutsche.de/stil/st-moritz-hotel-karussell-maison-mytheresa-skimode-li.3355684",
      "image_url": "https://www.sueddeutsche.de/2025/12/18/806bff11-42c2-46f8-8c00-25216c0b4264.jpg?rect=45,0,711,533&width=217&fm=jpeg&q=60"
    },
    {
      "title": "Treffen in China:Thailand und Kambodscha wollen Waffenruhe festigen",
      "url": "https://www.sueddeutsche.de/politik/treffen-in-china-thailand-und-kambodscha-wollen-waffenruhe-festigen-dpa.urn-newsml-dpa-com-20090101-251229-930-475392"
    },
    {
      "title": "Jahreswechsel:Silvester: Feuerwerksverbote in mehreren Thüringer Orten",
      "url": "https://www.sueddeutsche.de/panorama/jahreswechsel-silvester-feuerwerksverbote-in-mehreren-thueringer-orten-dpa.urn-newsml-dpa-com-20090101-251229-930-476000"
    },
    {
      "title": "Fälle mit hoher Priorität:Große Interpol-Fahndungsaktion führt zu 85 Festnahmen",
      "url": "https://www.sueddeutsche.de/panorama/faelle-mit-hoher-prioritaet-grosse-interpol-fahndungsaktion-fuehrt-zu-85-festnahmen-dpa.urn-newsml-dpa-com-20090101-251229-930-476852"
    },
    {
      "title": "Versuchter Totschlag:Mann greift Mitbewohner mit Messer an – Notoperation",
      "url": "https://www.sueddeutsche.de/panorama/versuchter-totschlag-mann-greift-mitbewohner-mit-messer-an-notoperation-dpa.urn-newsml-dpa-com-20090101-251229-930-476844"
    },
    {
      "title": "Migration:Weniger unerlaubte Einreisen - mehr Abschiebungen",
      "url": "https://www.sueddeutsche.de/bayern/migration-weniger-unerlaubte-einreisen-mehr-abschiebungen-dpa.urn-newsml-dpa-com-20090101-251229-930-474647"
    },
    {
      "title": "Lebensgefährte verletzt:Frau wehrt sich mit Messer gegen Übergriffe des Partners",
      "url": "https://www.sueddeutsche.de/panorama/lebensgefaehrte-verletzt-frau-wehrt-sich-mit-messer-gegen-uebergriffe-des-partners-dpa.urn-newsml-dpa-com-20090101-251229-930-476824"
    },
    {
      "title": "Kriminalität:59-Jähriger randaliert und wirft Wurfsterne auf Polizei",
      "url": "https://www.sueddeutsche.de/bayern/kriminalitaet-59-jaehriger-randaliert-und-wirft-wurfsterne-auf-polizei-dpa.urn-newsml-dpa-com-20090101-251229-930-476447"
    },
    {
      "title": "Brände:Millionenschaden bei Brand an Tegelbergbahn",
      "url": "https://www.sueddeutsche.de/bayern/braende-millionenschaden-bei-brand-an-tegelbergbahn-dpa.urn-newsml-dpa-com-20090101-251229-930-475054"
    },
    {
      "title": "SZ PlusKreuzworträtsel:15 mal 15 – füllt Ihr Wissen alle Felder?",
      "url": "https://www.sueddeutsche.de/raetsel/kreuzwortraetsel/",
      "image_url": "https://www.sueddeutsche.de/2024/03/18/c2ba0d6b-b70e-4674-9ac5-b474e484824a.png?rect=0,0,832,624&width=217&fm=png&q=60"
    },
    {
      "title": "Sudoku:1 bis 9 – bekommen Sie’s auf die Reihe?",
      "url": "https://www.sueddeutsche.de/raetsel/sudoku",
      "image_url": "https://www.sueddeutsche.de/2025/12/01/c31ccf96-fe85-4b66-9834-413af080d9eb.png?rect=0,0,832,624&width=217&fm=png&q=60"
    },
    {
      "title": "SZ PlusStr8ts:Bauen Sie Zahlenstraßen – kreuz und quer",
      "url": "https://www.sueddeutsche.de/raetsel/str8ts/",
      "image_url": "https://www.sueddeutsche.de/2025/04/11/75a4b485-76c2-4e57-8e26-254aaa3171d4.png?rect=0,0,832,624&width=217&fm=png&q=60"
    },
    {
      "title": "SZ PlusBuchstabenring:Bilden Sie Wörter – je weniger, desto besser",
      "url": "https://www.sueddeutsche.de/raetsel/buchstabenring/",
      "image_url": "https://www.sueddeutsche.de/2024/03/18/53356549-9d8e-4c7a-a2e3-8d53c738d1fc.png?rect=0,0,832,624&width=217&fm=png&q=60"
    },
    {
      "title": "SZ PlusFutoshiki:Füllen Sie das Quadrat – so, dass alles passt",
      "url": "https://www.sueddeutsche.de/raetsel/futoshiki/",
      "image_url": "https://www.sueddeutsche.de/2024/03/18/42756151-dcb3-4eb0-bf1d-6b0c8f1d1e97.png?rect=0,0,832,624&width=217&fm=png&q=60"
    },
    {
      "title": "SZ PlusQuartett:Vier Bilder, eine Gemeinsamkeit – welche?",
      "url": "https://www.sueddeutsche.de/raetsel/quartett/",
      "image_url": "https://www.sueddeutsche.de/2024/03/18/9bf7b4f6-c393-4613-867d-7aaac7e1de20.png?rect=0,0,832,624&width=217&fm=png&q=60"
    },
    {
      "title": "SZ PlusSchach:Sie sind am Zug – mit Tipps vom Großmeister",
      "url": "https://www.sueddeutsche.de/raetsel/schach/",
      "image_url": "https://www.sueddeutsche.de/2024/03/18/ff819e61-ef13-46ce-b5e6-7fd5351b6a4d.png?rect=0,0,832,624&width=217&fm=png&q=60"
    },
    {
      "title": "Mahjong:Der Legespiel-Klassiker aus China",
      "url": "https://www.sueddeutsche.de/app/spiele/mahjong/",
      "image_url": "https://www.sueddeutsche.de/2024/03/18/2eee34aa-8bdb-42fa-9ee5-c606d55a05e5.png?rect=0,0,832,624&width=217&fm=png&q=60"
    },
    {
      "title": "Exchange / Jewels:Juwelen mit Suchtgefahr",
      "url": "https://www.sueddeutsche.de/app/spiele/exchange/",
      "image_url": "https://www.sueddeutsche.de/2024/03/18/a9887f5e-6475-4cbb-b09f-a5793e9430a1.png?rect=0,0,832,624&width=217&fm=png&q=60"
    },
    {
      "title": "SZ PlusDas Kreuz mit den Worten:Das Kult-Rätsel aus dem SZ-Magazin",
      "url": "https://sz-magazin.sueddeutsche.de/tag/das-kreuz-mit-den-worten/",
      "image_url": "https://www.sueddeutsche.de/2024/03/18/bec6d319-95ed-45b2-a4ac-9edf57b89b9b.png?rect=0,0,832,624&width=217&fm=png&q=60"
    },
    {
      "title": "IQ-Test:Wie hoch ist Ihr Intelligenzquotient?",
      "url": "https://iqtest.sueddeutsche.de/",
      "image_url": "https://www.sueddeutsche.de/2024/03/18/9a4403ff-397d-47e4-a56e-a8eb2ae96727.png?rect=0,0,832,624&width=217&fm=png&q=60"
    },
    {
      "title": "Adventskalender:Alle Jahre wieder – das große Gewinnspiel",
      "url": "https://adventskalender.sueddeutsche.de/",
      "image_url": "https://www.sueddeutsche.de/2024/03/18/66f3c840-18b8-467e-98c9-2ad630088e8e.png?rect=0,0,832,624&width=217&fm=png&q=60"
    },
    {
      "title": "Führerscheintest:Schaffen Sie die Prüfung noch?",
      "url": "https://fuehrerschein.sueddeutsche.de/",
      "image_url": "https://www.sueddeutsche.de/2024/03/18/27aa7c14-a245-4753-b8e2-af9d4cf1f3ac.png?rect=0,0,832,624&width=217&fm=png&q=60"
    },
    {
      "title": "Einbürgerungstest:Dürften Sie deutscher Staatsbürger werden?",
      "url": "https://www.sueddeutsche.de/thema/Einb%C3%BCrgerungstest",
      "image_url": "https://www.sueddeutsche.de/2024/03/18/19e014bd-4262-4861-8505-3f993385f6ed.png?rect=0,0,832,624&width=217&fm=png&q=60"
    },
    {
      "title": "EQ-Test:Testen Sie Ihre emotionale Intelligenz",
      "url": "https://quiz.sueddeutsche.de/quiz/50ceff3b49fdf0baba67c8fd0ad08566-eq-test---pers-nlichkeitstest",
      "image_url": "https://www.sueddeutsche.de/2024/03/18/13c3aae4-93ba-417f-b4c7-587aa0a0abd8.png?rect=0,0,832,624&width=217&fm=png&q=60"
    },
    {
      "title": "Abnehmen:Wie Sie gesund Gewicht verlieren",
      "url": "https://www.sueddeutsche.de/thema/Abnehmen",
      "image_url": "https://www.sueddeutsche.de/2022/06/14/59db5bd4-c230-4e87-9e04-25ca0094412e.jpeg?rect=45,0,711,533&width=217&fm=jpeg&q=60"
    },
    {
      "title": "Tipps für das Leben mit Kindern:Ratgeber Erziehung",
      "url": "https://www.sueddeutsche.de/thema/Erziehung",
      "image_url": "https://www.sueddeutsche.de/2022/06/21/121329ca-2337-4092-bb90-d31615c8e51a.jpeg?rect=45,0,711,533&width=217&fm=jpeg&q=60"
    },
    {
      "title": "Testament:Den Nachlass so regeln, wie man will",
      "url": "http://www.sz.de/thema/Testament",
      "image_url": "https://www.sueddeutsche.de/2022/06/14/bd673f75-bc89-4e9f-846e-2e20fd7763a6.jpeg?rect=74,0,1200,900&width=217&fm=jpeg&q=60"
    },
    {
      "title": "Gehaltsverhandlung:So bekommen Sie mehr Gehalt",
      "url": "https://www.sueddeutsche.de/thema/Gehaltsverhandlung",
      "image_url": "https://www.sueddeutsche.de/2022/06/14/836c1af2-be54-457b-acf3-751d815dd863.jpeg?rect=0,50,800,600&width=217&fm=jpeg&q=60"
    },
    {
      "title": "Einbürgerungstest:Dürften Sie deutscher Staatsbürger werden?",
      "url": "https://www.sueddeutsche.de/thema/Einb%C3%BCrgerungstest",
      "image_url": "https://www.sueddeutsche.de/2024/03/18/19e014bd-4262-4861-8505-3f993385f6ed.png?rect=0,0,832,624&width=217&fm=png&q=60"
    },
    {
      "title": "Studium:Tipps für das Leben an der Universität",
      "url": "https://www.sueddeutsche.de/thema/Studium",
      "image_url": "https://www.sueddeutsche.de/2022/06/22/cb618253-d06f-4b54-ac35-8d0c74d55f70.jpeg?rect=0,50,800,600&width=217&fm=jpeg&q=60"
    },
    {
      "title": "Ratgeber Influenza:Der Grippe entkommen",
      "url": "http://www.sueddeutsche.de/thema/Grippe",
      "image_url": "https://www.sueddeutsche.de/2022/06/14/7cbc83bd-d9ca-4390-8b00-a9275878f834.jpeg?rect=94,0,755,566&width=217&fm=jpeg&q=60"
    },
    {
      "title": "Ratgeber Depression:Wege aus der Melancholie",
      "url": "https://www.sueddeutsche.de/thema/Depression",
      "image_url": "https://www.sueddeutsche.de/2022/06/15/54b5688d-25bd-48ec-9cb1-07ecf3baccf3.jpeg?rect=778,204,672,504&width=217&fm=jpeg&q=60"
    }
  ]
}